pychanio/__init__.py
pychanio/core.py
pychanio/dsl.py
pychanio/exceptions.py
pychanio/interfaces.py
pychanio/nil.py
pychanio/runners.py
pychanio/select.py
pychanio/sentinels.py
pychanio-0.1.3.dist-info/METADATA
pychanio-0.1.3.dist-info/WHEEL
pychanio-0.1.3.dist-info/entry_points.txt
pychanio-0.1.3.dist-info/licenses/LICENSE
pychanio-0.1.3.dist-info/RECORD
