Metadata-Version: 2.4
Name: pychanio
Version: 0.1.3
Summary: Go-style channels and select blocks for asyncio in Python.
Project-URL: Homepage, https://github.com/harsh098/pychanio
Project-URL: Issues, https://github.com/harsh098/pychanio/issues
Project-URL: Documentation, https://harsh-mishra.gitbook.io/pychanio
Author-email: Harsh Mishra <hmisraji07@gmail.com>
License: MIT
License-File: LICENSE
Requires-Python: >=3.12
